{
  "checklist_type": "7_fms",
  "category": "3. EP6 START & End of shift checklist",
  "machine_type": "EP6 Shroud Assembly (2)",
  "title": "FORM:-  START UP & END OF SHIFT CHECKLIST",
  "source_workbook": "7. FMS.xlsx",
  "metadata": {
    "shift": "",
    "condition": "",
    "date": ""
  },
  "sections": [
    {
      "title": "SHIFT START UP CHECK LIST :-",
      "items": [
        {
          "id": "activity_01",
          "serial_no": "1",
          "item": "",
          "question": "Clean Fixtures ,Tool & Working Area",
          "specified_value": "YES/NO",
          "answer_type": "YES/NO",
          "value": ""
        },
        {
          "id": "activity_02",
          "serial_no": "2",
          "item": "",
          "question": "OE Deploy as per skill matrix",
          "specified_value": "YES/NO",
          "answer_type": "YES/NO",
          "value": ""
        },
        {
          "id": "activity_03",
          "serial_no": "3",
          "item": "",
          "question": "Switch on power supply",
          "specified_value": "ON/OFF",
          "answer_type": "ON/OFF",
          "value": ""
        },
        {
          "id": "activity_04",
          "serial_no": "4",
          "item": "",
          "question": "Check the air pressure",
          "specified_value": "5 To 7 BAR",
          "answer_type": "Text",
          "value": ""
        },
        {
          "id": "activity_05",
          "serial_no": "5",
          "item": "",
          "question": "Wear personal protective equipments(PPE)",
          "specified_value": "DONE / NOT DONE",
          "answer_type": "DONE / NOT DONE",
          "value": ""
        },
        {
          "id": "activity_06",
          "serial_no": "6",
          "item": "",
          "question": "Check PM status of Workstation/Machine",
          "specified_value": "OK / NOT OK",
          "answer_type": "OK / NOT OK",
          "value": ""
        },
        {
          "id": "activity_07",
          "serial_no": "7",
          "item": "",
          "question": "Check the cundition of running model fixture/ tools & PM status  (Should be within due date mentioned)",
          "specified_value": "OK / NOT OK",
          "answer_type": "OK / NOT OK",
          "value": ""
        },
        {
          "id": "activity_08",
          "serial_no": "8",
          "item": "",
          "question": "Availability of rejection bin/Identification tags \n( Red/Yellow/Green)",
          "specified_value": "YES/NO",
          "answer_type": "YES/NO",
          "value": ""
        },
        {
          "id": "activity_09",
          "serial_no": "9",
          "item": "",
          "question": "Calibration of instruments",
          "specified_value": "YES/NO",
          "answer_type": "YES/NO",
          "value": ""
        }
      ]
    },
    {
      "title": "SHIFT START UP CHECK LIST :- - Poka Yoke Validation",
      "items": [
        {
          "id": "activity_10",
          "serial_no": "1",
          "item": "",
          "question": "Motor & shroud locking Nut/Screw gun torque achieving verification. For S201/S215 GSL/DSL,W153&Altroz  -Torque (2.2 to 3.0) NM for Nexon GSL/Curve (4.0 to 5.0)NM\nNote down in startup & endup report",
          "specified_value": "For NOT OK condition:- Do motor shroud locking screw half torque, FMS assembly will not get de-clamped and barcode will not Generate\nFor OK condiion:- Do motor shroud locking screw complete torque as per requirement, FMS assembly will not de-clamped and barcode will Generate | OK / NOT OK",
          "answer_type": "OK / NOT OK",
          "value": ""
        },
        {
          "id": "activity_11",
          "serial_no": "2",
          "item": "",
          "question": "Shroud & Resistor locking screws gun torque achieving verification. Torque (1.2 to 1.8) NM",
          "specified_value": "For NOT OK condition:- Do resistor locking screw half torque fan motor shroud assembly will not get de-clamped and barcode will not Generate\nFor OK condition:-Do resistor locking screw complete torque as per requirement  fan motor shroud assembly will get de-clamped and barcode will Generate | OK / NOT OK",
          "answer_type": "OK / NOT OK",
          "value": ""
        },
        {
          "id": "activity_12",
          "serial_no": "3",
          "item": "",
          "question": "Resister Colour Sensing POKAYOKE\n[ for S201/S215 DSL - Black Colour Resister\nS201/S215 GSL - White Colour Resister ] For NOT OK Condition : FMS Assembly will not get clamped if specified color resister is not fixed on Shroud.  \nFor OK Condition : FMS Assembly will get clamped if specified color resister is fixed on Shroud.",
          "specified_value": "OK / NOT OK",
          "answer_type": "OK / NOT OK",
          "value": ""
        },
        {
          "id": "activity_13",
          "serial_no": "4",
          "item": "",
          "question": "Poka-yoke is been added in the fixture to differential between S201/S215 shroud For OK Condition: Check the block position should be in front and sensore should be in on condition for S215 model.",
          "specified_value": "OK / NOT OK",
          "answer_type": "OK / NOT OK",
          "value": ""
        },
        {
          "id": "activity_14",
          "serial_no": "5",
          "item": "",
          "question": "Motor Barcode Scanning (As per Model)",
          "specified_value": "For NOT OK Condition : FMS Assembly will not get clamped and Gun will not Active if Motor Barcode not scanned by Scanner. \nFor OK Condition : FMS Assembly will  get clamped and Gun will  Active if Motor Barcode scanned by Scanner. | OK / NOT OK",
          "answer_type": "OK / NOT OK",
          "value": ""
        }
      ]
    },
    {
      "title": "END OF SHIFT CHECK POINTS :-",
      "items": [
        {
          "id": "activity_15",
          "serial_no": "1",
          "item": "",
          "question": "Clean Fixtures ,Tool & Working Area",
          "specified_value": "YES/NO",
          "answer_type": "YES/NO",
          "value": ""
        },
        {
          "id": "activity_16",
          "serial_no": "2",
          "item": "",
          "question": "Removal and Record of rejection",
          "specified_value": "YES/NO",
          "answer_type": "YES/NO",
          "value": ""
        },
        {
          "id": "activity_17",
          "serial_no": "3",
          "item": "",
          "question": "Switch off power supply",
          "specified_value": "ON/OFF",
          "answer_type": "ON/OFF",
          "value": ""
        }
      ]
    },
    {
      "title": "END OF SHIFT CHECK POINTS :- - Poka Yoke Validation",
      "items": [
        {
          "id": "activity_18",
          "serial_no": "1",
          "item": "",
          "question": "Motor & shroud locking Nut/Screw gun torque achieving verification. For S201/S215 GSL/DSL,W153&Altroz  -Torque (2.2 to 3.0) NM for Nexon GSL/Curve (4.0 to 5.0)NM\nNote down in startup & endup report",
          "specified_value": "For NOT OK condition:- Do motor shroud locking screw half torque, FMS assembly will not get de-clamped and barcode will not Generate\nFor OK condiion:- Do motor shroud locking screw complete torque as per requirement, FMS assembly will not de-clamped and barcode will Generate | OK / NOT OK",
          "answer_type": "OK / NOT OK",
          "value": ""
        },
        {
          "id": "activity_19",
          "serial_no": "2",
          "item": "",
          "question": "Shroud & Resistor locking screws gun torque achieving verification. Torque (1.2 to 1.8) NM for other model",
          "specified_value": "For NOT OK condition:- Do resistor locking screw half torque fan motor shroud assembly will not get de-clamped and barcode will not Generate\nFor OK condition:-Do resistor locking screw complete torque as per requirement  fan motor shroud assembly will get de-clamped and barcode will Generate | OK / NOT OK",
          "answer_type": "OK / NOT OK",
          "value": ""
        },
        {
          "id": "activity_20",
          "serial_no": "3",
          "item": "",
          "question": "Resister Colour Sensing POKAYOKE\n[ for S201/S215 DSL - Black Colour Resister\nS201/S215 GSL - White Colour Resister ] For NOT OK Condition : FMS Assembly will not get clamped if specified color resister is not fixed on Shroud.  \nFor OK Condition : FMS Assembly will get clamped if specified color resister is fixed on Shroud.",
          "specified_value": "OK / NOT OK",
          "answer_type": "OK / NOT OK",
          "value": ""
        },
        {
          "id": "activity_21",
          "serial_no": "4",
          "item": "",
          "question": "Poka-yoke is been added in the fixture to differential between S201/S215 shroud For OK Condition: Check the block position should be in front and sensore should be in on condition for S215 model.",
          "specified_value": "OK / NOT OK",
          "answer_type": "OK / NOT OK",
          "value": ""
        },
        {
          "id": "activity_22",
          "serial_no": "5",
          "item": "",
          "question": "Motor Barcode Scanning (As per Model)",
          "specified_value": "For NOT OK Condition : FMS Assembly will not get clamped and Gun will not Active if Motor Barcode not scanned by Scanner. \nFor OK Condition : FMS Assembly will  get clamped and Gun will  Active if Motor Barcode scanned by Scanner. | OK / NOT OK",
          "answer_type": "OK / NOT OK",
          "value": ""
        }
      ]
    }
  ],
  "summary": {
    "summary_shift_start_up_check_list_name_sign_of_person_attending": "",
    "summary_shift_start_up_check_list_name_sign_of_approving_cell_coordinator": "",
    "summary_end_of_shift_check_points_name_sign_of_person_attending": "",
    "summary_end_of_shift_check_points_name_sign_of_approving_cell_coordinator": ""
  }
}